qelrix/__init__.py
qelrix/qelrix.py
qelrix-0.0.1.dist-info/METADATA
qelrix-0.0.1.dist-info/WHEEL
qelrix-0.0.1.dist-info/top_level.txt
qelrix-0.0.1.dist-info/RECORD
